{
    "AwsAccountId": "${account}",
    "DashboardId": "${dashboardId}",
    "Name": "Trusted Advisor Organizational View",
    "Permissions": [
        {
          "Principal": "${user_arn}",
          "Actions": [
            "quicksight:DescribeDashboard",
            "quicksight:ListDashboardVersions",
            "quicksight:UpdateDashboardPermissions",
            "quicksight:QueryDashboard",
            "quicksight:UpdateDashboard",
            "quicksight:DeleteDashboard",
            "quicksight:DescribeDashboardPermissions",
            "quicksight:UpdateDashboardPublishedVersion"
          ]
        }
      ],
      "DashboardPublishOptions": {
        "AdHocFilteringOption": {
          "AvailabilityStatus": "DISABLED"
        }
      },
    "SourceEntity": {
        "SourceTemplate": {
            "DataSetReferences": [
                {
                    "DataSetPlaceholder": "ta-organizational-view",
                    "DataSetArn": "arn:aws:quicksight:${region}:${account}:dataset/${dataSetId}"
                }
            ],
            "Arn": "arn:aws:quicksight:us-east-1:${sourceAccountId}:template/${sourceTemplateId}"
        }
    },
    "VersionDescription": "1"
}
