{
    "yes": [
        {
            "Type": "string",
            "Name": "source_account_id"
        },
        {
            "Type": "string",
            "Name": "cur_name_1"
        },
        {
            "Type": "string",
            "Name": "cur_name_2"
        },
        {
            "Type": "string",
            "Name": "year"
        },
        {
            "Type": "string",
            "Name": "month"
        }
    ],
    "no": [
        {
            "Type": "string",
            "Name": "year"
        },
        {
            "Type": "string",
            "Name": "month"
        }
    ]
}